bellows/__init__.py
bellows/ash.py
bellows/exception.py
bellows/multicast.py
bellows/thread.py
bellows/typing.py
bellows/uart.py
bellows/cli/__init__.py
bellows/cli/application.py
bellows/cli/backup.py
bellows/cli/dump.py
bellows/cli/main.py
bellows/cli/ncp.py
bellows/cli/network.py
bellows/cli/opts.py
bellows/cli/stream.py
bellows/cli/tone.py
bellows/cli/util.py
bellows/config/__init__.py
bellows/ezsp/__init__.py
bellows/ezsp/config.py
bellows/ezsp/fragmentation.py
bellows/ezsp/protocol.py
bellows/ezsp/xncp.py
bellows/ezsp/v10/__init__.py
bellows/ezsp/v10/commands.py
bellows/ezsp/v10/config.py
bellows/ezsp/v11/__init__.py
bellows/ezsp/v11/commands.py
bellows/ezsp/v11/config.py
bellows/ezsp/v12/__init__.py
bellows/ezsp/v12/commands.py
bellows/ezsp/v12/config.py
bellows/ezsp/v13/__init__.py
bellows/ezsp/v13/commands.py
bellows/ezsp/v13/config.py
bellows/ezsp/v14/__init__.py
bellows/ezsp/v14/commands.py
bellows/ezsp/v14/config.py
bellows/ezsp/v16/__init__.py
bellows/ezsp/v16/commands.py
bellows/ezsp/v16/config.py
bellows/ezsp/v17/__init__.py
bellows/ezsp/v17/commands.py
bellows/ezsp/v17/config.py
bellows/ezsp/v4/__init__.py
bellows/ezsp/v4/commands.py
bellows/ezsp/v4/config.py
bellows/ezsp/v5/__init__.py
bellows/ezsp/v5/commands.py
bellows/ezsp/v5/config.py
bellows/ezsp/v6/__init__.py
bellows/ezsp/v6/commands.py
bellows/ezsp/v6/config.py
bellows/ezsp/v7/__init__.py
bellows/ezsp/v7/commands.py
bellows/ezsp/v7/config.py
bellows/ezsp/v8/__init__.py
bellows/ezsp/v8/commands.py
bellows/ezsp/v8/config.py
bellows/ezsp/v9/__init__.py
bellows/ezsp/v9/commands.py
bellows/ezsp/v9/config.py
bellows/types/__init__.py
bellows/types/basic.py
bellows/types/named.py
bellows/types/struct.py
bellows/zigbee/__init__.py
bellows/zigbee/application.py
bellows/zigbee/device.py
bellows/zigbee/repairs.py
bellows/zigbee/util.py
bellows-0.48.2.dist-info/licenses/COPYING
bellows-0.48.2.dist-info/licenses/LICENSE
bellows-0.48.2.dist-info/METADATA
bellows-0.48.2.dist-info/WHEEL
bellows-0.48.2.dist-info/entry_points.txt
bellows-0.48.2.dist-info/top_level.txt
bellows-0.48.2.dist-info/RECORD
