Metadata-Version: 2.4
Name: bellows
Version: 0.48.2
Summary: Library implementing EZSP
Author-email: Russell Cloran <rcloran@gmail.com>
License: GPL-3.0
Project-URL: repository, https://github.com/zigpy/bellows
Requires-Python: >=3.11
License-File: LICENSE
License-File: COPYING
Requires-Dist: click
Requires-Dist: click-log>=0.2.1
Requires-Dist: voluptuous
Requires-Dist: zigpy>=0.87.0
Provides-Extra: testing
Requires-Dist: pytest>=7.1.2; extra == "testing"
Requires-Dist: pytest-asyncio>=0.19.0; extra == "testing"
Requires-Dist: pytest-timeout>=2.1.0; extra == "testing"
Requires-Dist: pytest-mock>=3.8.2; extra == "testing"
Requires-Dist: pytest-cov>=3.0.0; extra == "testing"
Dynamic: license-file
